crenametoix/__init__.py
crenametoix/crenametoix.py
crenametoix/plugins/__init__.py
crenametoix/plugins/doc.py
crenametoix/plugins/geo.py
crenametoix-1.4.1.dist-info/METADATA
crenametoix-1.4.1.dist-info/WHEEL
crenametoix-1.4.1.dist-info/entry_points.txt
crenametoix-1.4.1.dist-info/top_level.txt
crenametoix-1.4.1.dist-info/RECORD
