Metadata-Version: 2.1
Name: crenametoix
Version: 1.4.1
Summary: Linux file renamer featuring an advanced macro ecosystem
Author-email: Alexandre Bento Freire <devtoix@a-bentofreire.com>
Project-URL: Homepage, https://www.devtoix.com/en/projects/renametoix
Project-URL: Repository, https://github.com/a-bentofreire/renametoix
Project-URL: Issues, https://github.com/a-bentofreire/renametoix/issues
Project-URL: Changelog, https://github.com/a-bentofreire/renametoix/blob/HEAD/CHANGELOG.md
Project-URL: Twitter, https://x.com/devtoix
Keywords: linux,rename,file
Classifier: Programming Language :: Python :: 3
Classifier: License :: OSI Approved :: MIT License
Classifier: Operating System :: OS Independent
Requires-Python: >=3.9
